{
    "Page": 1,
    "Blocks": [
        {
            "BlockType": "LINE",
            "Confidnece": 99.44297790527344,
            "Text": "3.2.7. Summary of Mapping Issues",
            "BoundingBox": {
                "Width": 0.24748189747333527,
                "Height": 0.011590356007218361,
                "Left": 0.20425358414649963,
                "Top": 0.17599590122699738
            },
            "Id": "524bc837-02ac-460a-bd80-5bb986bc3168",
            "Quadrant": "Q1",
            "height_diff_above": 0,
            "height_diff_below": 0.002213751897215843,
            "paragraph": 0,
            "paragraph_std": 0,
            "top_scl": 0.0,
            "paragraph_scl": 0.0,
            "left_scl": 0.013440547937568326,
            "paragraph_std_scl": 0.0,
            "text_cluster": 0,
            "cluster_probability": 0.46260898335534745
        },
        {
            "BlockType": "LINE",
            "Confidnece": 99.93960571289062,
            "Text": "The issue of mapping Chinese and English role designators is more than a translation",
            "BoundingBox": {
                "Width": 0.5723719596862793,
                "Height": 0.0117711890488863,
                "Left": 0.22314471006393433,
                "Top": 0.18980000913143158
            },
            "Id": "063f5c9e-207a-4891-980a-d87b66d8bd04",
            "Quadrant": "Q1",
            "height_diff_above": 0.002213751897215843,
            "height_diff_below": 0.0018758755177259445,
            "paragraph": 0,
            "paragraph_std": 0,
            "top_scl": 0.04809758975197953,
            "paragraph_scl": 0.0,
            "left_scl": 0.9952565049773785,
            "paragraph_std_scl": 0.0,
            "text_cluster": -1,
            "cluster_probability": 0.0
        },
        {
            "BlockType": "LINE",
            "Confidnece": 99.7789077758789,
            "Text": "issue. We can see how different cultural regions represent creators and contributors",
            "BoundingBox": {
                "Width": 0.5900446176528931,
                "Height": 0.011600515805184841,
                "Left": 0.20441259443759918,
                "Top": 0.20344707369804382
            },
            "Id": "e2823dbd-c6c3-454c-a0c6-7b119c88c60c",
            "Quadrant": "Q1",
            "height_diff_above": 0.0018758755177259445,
            "height_diff_below": 0.0020718956366181374,
            "paragraph": 0,
            "paragraph_std": 0,
            "top_scl": 0.09564799412348135,
            "paragraph_scl": 0.0,
            "left_scl": 0.021704684327183088,
            "paragraph_std_scl": 0.0,
            "text_cluster": 0,
            "cluster_probability": 0.7549080064314667
        },
        {
            "BlockType": "LINE",
            "Confidnece": 99.83830261230469,
            "Text": "differently. For instance, if a Chinese term can be interpreted as both editor and compiler,",
            "BoundingBox": {
                "Width": 0.5903813242912292,
                "Height": 0.01159003283828497,
                "Left": 0.2040727585554123,
                "Top": 0.2171194851398468
            },
            "Id": "9b458e9b-b246-4edc-bd6d-acc54a868b37",
            "Quadrant": "Q1",
            "height_diff_above": 0.0020718956366181374,
            "height_diff_below": 0.0021552899852395058,
            "paragraph": 0,
            "paragraph_std": 0,
            "top_scl": 0.14328671449576058,
            "paragraph_scl": 0.0,
            "left_scl": 0.004042619431524841,
            "paragraph_std_scl": 0.0,
            "text_cluster": 0,
            "cluster_probability": 1.0
        },
        {
            "BlockType": "LINE",
            "Confidnece": 98.34756469726562,
            "Text": "why is it so? Does that mean people do not distinguish the two roles, SO the language",
            "BoundingBox": {
                "Width": 0.5904844999313354,
                "Height": 0.011570033617317677,
                "Left": 0.20428867638111115,
                "Top": 0.23086480796337128
            },
            "Id": "5e86edfe-0e56-4025-9292-b29eb71d95ce",
            "Quadrant": "Q1",
            "height_diff_above": 0.0021552899852395058,
            "height_diff_below": 0.0019440678879618645,
            "paragraph": 0,
            "paragraph_std": 0,
            "top_scl": 0.19117947966039928,
            "paragraph_scl": 0.0,
            "left_scl": 0.015264373370754925,
            "paragraph_std_scl": 0.0,
            "text_cluster": 0,
            "cluster_probability": 1.0
        },
        {
            "BlockType": "LINE",
            "Confidnece": 99.94658660888672,
            "Text": "allows and represents the ambiguity? On the contrary, if a Chinese term is very specific",
            "BoundingBox": {
                "Width": 0.59076988697052,
                "Height": 0.0118543216958642,
                "Left": 0.20433636009693146,
                "Top": 0.24437890946865082
            },
            "Id": "e4b20235-d970-4398-9306-13a7b594fd37",
            "Quadrant": "Q1",
            "height_diff_above": 0.0019440678879618645,
            "height_diff_below": 0.0018558939918875694,
            "paragraph": 0,
            "paragraph_std": 0,
            "top_scl": 0.23826660144816436,
            "paragraph_scl": 0.0,
            "left_scl": 0.017742607505022434,
            "paragraph_std_scl": 0.0,
            "text_cluster": 0,
            "cluster_probability": 1.0
        },
        {
            "BlockType": "LINE",
            "Confidnece": 99.95999908447266,
            "Text": "about a role that is difficult to find an English counterpart, does that mean the role is",
            "BoundingBox": {
                "Width": 0.5904960036277771,
                "Height": 0.011663860641419888,
                "Left": 0.20427115261554718,
                "Top": 0.2580891251564026
            },
            "Id": "34ba3d07-7414-487f-918d-d93c2b66fb39",
            "Quadrant": "Q1",
            "height_diff_above": 0.0018558939918875694,
            "height_diff_below": 0.0021382803097367287,
            "paragraph": 0,
            "paragraph_std": 0,
            "top_scl": 0.28603704298092103,
            "paragraph_scl": 0.0,
            "left_scl": 0.014353622326412463,
            "paragraph_std_scl": 0.0,
            "text_cluster": 0,
            "cluster_probability": 1.0
        },
        {
            "BlockType": "LINE",
            "Confidnece": 99.92988586425781,
            "Text": "important enough to have a specific term created? The mapping issue surfaces a conflict",
            "BoundingBox": {
                "Width": 0.5904730558395386,
                "Height": 0.011590438894927502,
                "Left": 0.20455308258533478,
                "Top": 0.2718912661075592
            },
            "Id": "63c32c74-7aeb-4d45-86c8-4bb068adf8d9",
            "Quadrant": "Q1",
            "height_diff_above": 0.0021382803097367287,
            "height_diff_below": 0.0020832838490605354,
            "paragraph": 0,
            "paragraph_std": 0,
            "top_scl": 0.33412777928663207,
            "paragraph_scl": 0.0,
            "left_scl": 0.02900618164526847,
            "paragraph_std_scl": 0.0,
            "text_cluster": 0,
            "cluster_probability": 1.0
        },
        {
            "BlockType": "LINE",
            "Confidnece": 99.89527893066406,
            "Text": "between standard warrant and content and cultural warrant. Catalogers describing",
            "BoundingBox": {
                "Width": 0.5905781984329224,
                "Height": 0.011441209353506565,
                "Left": 0.2041633129119873,
                "Top": 0.28556498885154724
            },
            "Id": "3e0359f2-e209-4dd7-a590-4f7de1bf352a",
            "Quadrant": "Q1",
            "height_diff_above": 0.0020832838490605354,
            "height_diff_below": 0.0019456660374999046,
            "paragraph": 0,
            "paragraph_std": 0,
            "top_scl": 0.3817710686230903,
            "paragraph_scl": 0.0,
            "left_scl": 0.008748940942131966,
            "paragraph_std_scl": 0.0,
            "text_cluster": 0,
            "cluster_probability": 1.0
        },
        {
            "BlockType": "LINE",
            "Confidnece": 99.94013214111328,
            "Text": "Chinese materials in the U.S. context may struggle between conforming with U.S.",
            "BoundingBox": {
                "Width": 0.5895901322364807,
                "Height": 0.011837001889944077,
                "Left": 0.20425553619861603,
                "Top": 0.2989518642425537
            },
            "Id": "6f7eff3f-722d-4be3-be0f-04041c412911",
            "Quadrant": "Q1",
            "height_diff_above": 0.0019456660374999046,
            "height_diff_below": 0.0017358995974063873,
            "paragraph": 0,
            "paragraph_std": 0,
            "top_scl": 0.4284148970454016,
            "paragraph_scl": 0.0,
            "left_scl": 0.013542000647438712,
            "paragraph_std_scl": 0.0,
            "text_cluster": 0,
            "cluster_probability": 1.0
        },
        {
            "BlockType": "LINE",
            "Confidnece": 99.69161224365234,
            "Text": "cataloging practices and standards, which risk losing meanings; and faithful descriptions,",
            "BoundingBox": {
                "Width": 0.5902377367019653,
                "Height": 0.01163384411484003,
                "Left": 0.20416657626628876,
                "Top": 0.3125247657299042
            },
            "Id": "16d67f24-ea0b-4a7d-861f-526bd4ead036",
            "Quadrant": "Q1",
            "height_diff_above": 0.0017358995974063873,
            "height_diff_below": 0.002274869941174984,
            "paragraph": 0,
            "paragraph_std": 0,
            "top_scl": 0.47570689534055477,
            "paragraph_scl": 0.0,
            "left_scl": 0.008918545090695673,
            "paragraph_std_scl": 0.0,
            "text_cluster": 0,
            "cluster_probability": 1.0
        },
        {
            "BlockType": "LINE",
            "Confidnece": 99.92987823486328,
            "Text": "which require extra research and proposing new terms.",
            "BoundingBox": {
                "Width": 0.36731094121932983,
                "Height": 0.01157384179532528,
                "Left": 0.20443791151046753,
                "Top": 0.3264334797859192
            },
            "Id": "cbb4c400-22b7-459d-b08f-0f3b10b2fc7a",
            "Quadrant": "Q1",
            "height_diff_above": 0.002274869941174984,
            "height_diff_below": 0.015595594421029091,
            "paragraph": 0,
            "paragraph_std": 0,
            "top_scl": 0.5241689638259011,
            "paragraph_scl": 0.0,
            "left_scl": 0.023020471762846384,
            "paragraph_std_scl": 0.0,
            "text_cluster": 0,
            "cluster_probability": 0.757075875485845
        },
        {
            "BlockType": "LINE",
            "Confidnece": 99.77365112304688,
            "Text": "3.3. Rubbings",
            "BoundingBox": {
                "Width": 0.09884923696517944,
                "Height": 0.01150990929454565,
                "Left": 0.20425759255886078,
                "Top": 0.35360291600227356
            },
            "Id": "33524cb6-d8d6-49bb-a798-3c22b32b66aa",
            "Quadrant": "Q1",
            "height_diff_above": 0.015595594421029091,
            "height_diff_below": 0.002212689258158207,
            "paragraph": 1,
            "paragraph_std": 1,
            "top_scl": 0.6188353056115239,
            "paragraph_scl": 1.0,
            "left_scl": 0.013648874494480268,
            "paragraph_std_scl": 1.0,
            "text_cluster": 1,
            "cluster_probability": 0.4013854580547772
        },
        {
            "BlockType": "LINE",
            "Confidnece": 99.79065704345703,
            "Text": "Rubbings are a special material form that challenge the FRBR WEMI model.",
            "BoundingBox": {
                "Width": 0.5713528990745544,
                "Height": 0.01161668449640274,
                "Left": 0.22323597967624664,
                "Top": 0.3673255145549774
            },
            "Id": "05d6c5c9-a767-44d2-99c1-bc202e6a969e",
            "Quadrant": "Q1",
            "height_diff_above": 0.002212689258158207,
            "height_diff_below": 0.0021681711077690125,
            "paragraph": 1,
            "paragraph_std": 1,
            "top_scl": 0.6666488927037433,
            "paragraph_scl": 1.0,
            "left_scl": 1.0,
            "paragraph_std_scl": 1.0,
            "text_cluster": -1,
            "cluster_probability": 0.0
        },
        {
            "BlockType": "LINE",
            "Confidnece": 99.88690948486328,
            "Text": "Rubbings are a form created based on an original artwork, which could be a portrait or",
            "BoundingBox": {
                "Width": 0.5918835401535034,
                "Height": 0.011575054377317429,
                "Left": 0.20418544113636017,
                "Top": 0.38111037015914917
            },
            "Id": "318451ec-b590-4e5f-8951-ed8ff4c5f942",
            "Quadrant": "Q1",
            "height_diff_above": 0.0021681711077690125,
            "height_diff_below": 0.002209354192018509,
            "paragraph": 1,
            "paragraph_std": 1,
            "top_scl": 0.7146794017543681,
            "paragraph_scl": 1.0,
            "left_scl": 0.009898996470065313,
            "paragraph_std_scl": 1.0,
            "text_cluster": 1,
            "cluster_probability": 0.6338505737530549
        },
        {
            "BlockType": "LINE",
            "Confidnece": 99.86995697021484,
            "Text": "calligraphy created by an artist or a calligrapher. For long term preservation, the owner",
            "BoundingBox": {
                "Width": 0.5906543135643005,
                "Height": 0.011590521782636642,
                "Left": 0.204145610332489,
                "Top": 0.3948947787284851
            },
            "Id": "466faea4-f58f-4da0-9b0d-922ab8266356",
            "Quadrant": "Q1",
            "height_diff_above": 0.002209354192018509,
            "height_diff_below": 0.0018647797405719757,
            "paragraph": 1,
            "paragraph_std": 1,
            "top_scl": 0.7627083532035683,
            "paragraph_scl": 1.0,
            "left_scl": 0.007828896519784578,
            "paragraph_std_scl": 1.0,
            "text_cluster": 1,
            "cluster_probability": 1.0
        },
        {
            "BlockType": "LINE",
            "Confidnece": 99.83135986328125,
            "Text": "of the artwork hired an engraver to carve a representation of it on a stele, hoping the",
            "BoundingBox": {
                "Width": 0.5902753472328186,
                "Height": 0.011752902530133724,
                "Left": 0.20423254370689392,
                "Top": 0.4083500802516937
            },
            "Id": "4c113ec8-0583-4472-aea1-39a61e348383",
            "Quadrant": "Q1",
            "height_diff_above": 0.0018647797405719757,
            "height_diff_below": 0.001994551159441471,
            "paragraph": 1,
            "paragraph_std": 1,
            "top_scl": 0.8095905984839451,
            "paragraph_scl": 1.0,
            "left_scl": 0.012347027125821697,
            "paragraph_std_scl": 1.0,
            "text_cluster": 1,
            "cluster_probability": 1.0
        },
        {
            "BlockType": "LINE",
            "Confidnece": 99.89911651611328,
            "Text": "transformation of medium would extend the longevity of the artwork. However, steles",
            "BoundingBox": {
                "Width": 0.5909806489944458,
                "Height": 0.011591886170208454,
                "Left": 0.2039949744939804,
                "Top": 0.4220975339412689
            },
            "Id": "3d12af2b-eb99-4921-bb98-7200e8023f8e",
            "Quadrant": "Q1",
            "height_diff_above": 0.001994551159441471,
            "height_diff_below": 0.00202989112585783,
            "paragraph": 1,
            "paragraph_std": 1,
            "top_scl": 0.8574907882153746,
            "paragraph_scl": 1.0,
            "left_scl": 0.0,
            "paragraph_std_scl": 1.0,
            "text_cluster": 1,
            "cluster_probability": 1.0
        },
        {
            "BlockType": "LINE",
            "Confidnece": 99.85426330566406,
            "Text": "were often placed outdoors and they decayed over time. To further preserve the artwork,",
            "BoundingBox": {
                "Width": 0.5898230671882629,
                "Height": 0.01195134874433279,
                "Left": 0.20427419245243073,
                "Top": 0.4357193112373352
            },
            "Id": "b9cada95-274b-4392-a880-63b594c3784c",
            "Quadrant": "Q1",
            "height_diff_above": 0.00202989112585783,
            "height_diff_below": 0.0018535638228058815,
            "paragraph": 1,
            "paragraph_std": 1,
            "top_scl": 0.904953084266289,
            "paragraph_scl": 1.0,
            "left_scl": 0.014511609752471344,
            "paragraph_std_scl": 1.0,
            "text_cluster": 1,
            "cluster_probability": 1.0
        },
        {
            "BlockType": "LINE",
            "Confidnece": 99.37711334228516,
            "Text": "people may ask a technician to create rubbings from a stele - by attaching a paper to the",
            "BoundingBox": {
                "Width": 0.5908282399177551,
                "Height": 0.011737186461687088,
                "Left": 0.2040427178144455,
                "Top": 0.4495242238044739
            },
            "Id": "7be363dc-5cf7-4b49-8f80-3baf2948682d",
            "Quadrant": "Q1",
            "height_diff_above": 0.0018535638228058815,
            "height_diff_below": 0.0017365626990795135,
            "paragraph": 1,
            "paragraph_std": 1,
            "top_scl": 0.9530534777008328,
            "paragraph_scl": 1.0,
            "left_scl": 0.0024813319269352263,
            "paragraph_std_scl": 1.0,
            "text_cluster": 1,
            "cluster_probability": 1.0
        },
        {
            "BlockType": "LINE",
            "Confidnece": 99.91023254394531,
            "Text": "stele and padding inks to the paper, the content of the stele could be transferred and",
            "BoundingBox": {
                "Width": 0.5902767777442932,
                "Height": 0.011851009912788868,
                "Left": 0.20449841022491455,
                "Top": 0.4629979729652405
            },
            "Id": "17488e08-8b57-4040-ba89-b8df26704580",
            "Quadrant": "Q1",
            "height_diff_above": 0.0017365626990795135,
            "height_diff_below": 0,
            "paragraph": 1,
            "paragraph_std": 1,
            "top_scl": 1.0,
            "paragraph_scl": 1.0,
            "left_scl": 0.026164731320697854,
            "paragraph_std_scl": 1.0,
            "text_cluster": 1,
            "cluster_probability": 0.6563821576023634
        },
        {
            "BlockType": "LINE",
            "Confidnece": 99.71424102783203,
            "Text": "Wan-Chen Lee. 2017. Conflicts of Samantic Warrants in Cataloging Practices.",
            "BoundingBox": {
                "Width": 0.4759172201156616,
                "Height": 0.010990804061293602,
                "Left": 0.49928638339042664,
                "Top": 0.03623849153518677
            },
            "Id": "ad209f83-d620-43fe-bcf0-b30cb48d447b",
            "Quadrant": "Q2",
            "height_diff_above": 0,
            "height_diff_below": 0.002218184992671013,
            "paragraph": 0,
            "paragraph_std": 0,
            "top_scl": 0.0,
            "paragraph_scl": 0.0,
            "left_scl": 1.0,
            "paragraph_std_scl": 0.0,
            "text_cluster": -1,
            "cluster_probability": 0.0
        },
        {
            "BlockType": "LINE",
            "Confidnece": 97.93717956542969,
            "Text": "NASKO, Vol. 6. pp. 231-238.",
            "BoundingBox": {
                "Width": 0.1813601553440094,
                "Height": 0.010756910778582096,
                "Left": 0.4992857575416565,
                "Top": 0.04944748058915138
            },
            "Id": "657e1386-c0f3-4c65-b61d-f18de2dbefc0",
            "Quadrant": "Q2",
            "height_diff_above": 0.002218184992671013,
            "height_diff_below": 0.08398197125643492,
            "paragraph": 0,
            "paragraph_std": 0,
            "top_scl": 0.12236451650886587,
            "paragraph_scl": 0.0,
            "left_scl": 0.9998561515751447,
            "paragraph_std_scl": 0.0,
            "text_cluster": -1,
            "cluster_probability": 0.0
        },
        {
            "BlockType": "LINE",
            "Confidnece": 99.83893585205078,
            "Text": "6",
            "BoundingBox": {
                "Width": 0.010059908963739872,
                "Height": 0.010199028998613358,
                "Left": 0.49493563175201416,
                "Top": 0.1441863626241684
            },
            "Id": "ef6097a0-ec3d-4da0-9b55-88fdfa9bbc9a",
            "Quadrant": "Q2",
            "height_diff_above": 0.08398197125643492,
            "height_diff_below": 0,
            "paragraph": 1,
            "paragraph_std": 0,
            "top_scl": 1.0,
            "paragraph_scl": 1.0,
            "left_scl": 0.0,
            "paragraph_std_scl": 0.0,
            "text_cluster": -1,
            "cluster_probability": 0.0
        },
        {
            "BlockType": "LINE",
            "Confidnece": 99.91976928710938,
            "Text": "preserved through the rubbing. People could create multiple rubbings from the same stele",
            "BoundingBox": {
                "Width": 0.5899051427841187,
                "Height": 0.011899774894118309,
                "Left": 0.20436958968639374,
                "Top": 0.4765797257423401
            },
            "Id": "cd8f12cb-5f64-43ff-a310-7b2012e82f8f",
            "Quadrant": "Q3",
            "height_diff_above": 0,
            "height_diff_below": 0.0013948027044534683,
            "paragraph": 0,
            "paragraph_std": 0,
            "top_scl": 0.0,
            "paragraph_scl": 0.0,
            "left_scl": 0.024741545858661063,
            "paragraph_std_scl": 0.0,
            "text_cluster": 2,
            "cluster_probability": 0.09575197608572719
        },
        {
            "BlockType": "LINE",
            "Confidnece": 99.94354248046875,
            "Text": "at different times. There is no guarantee that the conditions of the stele remained identical",
            "BoundingBox": {
                "Width": 0.5895829796791077,
                "Height": 0.011774091981351376,
                "Left": 0.20453207194805145,
                "Top": 0.48987430334091187
            },
            "Id": "9d633d28-2c79-4dc8-8a12-861c2f99e6aa",
            "Quadrant": "Q3",
            "height_diff_above": 0.0013948027044534683,
            "height_diff_below": 0.0024137208238244057,
            "paragraph": 0,
            "paragraph_std": 0,
            "top_scl": 0.04228235947569314,
            "paragraph_scl": 0.0,
            "left_scl": 0.028906452320148546,
            "paragraph_std_scl": 0.0,
            "text_cluster": 2,
            "cluster_probability": 0.10393473264515872
        },
        {
            "BlockType": "LINE",
            "Confidnece": 99.90239715576172,
            "Text": "when the rubbings were created.",
            "BoundingBox": {
                "Width": 0.2173309475183487,
                "Height": 0.011346406303346157,
                "Left": 0.20442719757556915,
                "Top": 0.5040621161460876
            },
            "Id": "9881e737-7292-4452-9fc9-319e77e2a6f6",
            "Quadrant": "Q3",
            "height_diff_above": 0.0024137208238244057,
            "height_diff_below": 0.0021430784836411476,
            "paragraph": 0,
            "paragraph_std": 1,
            "top_scl": 0.08740558334304871,
            "paragraph_scl": 0.0,
            "left_scl": 0.026218208402691623,
            "paragraph_std_scl": 0.5,
            "text_cluster": 2,
            "cluster_probability": 0.36625327320729045
        },
        {
            "BlockType": "LINE",
            "Confidnece": 99.73009490966797,
            "Text": "In an observation session, Q showed me her explanation and application of the FRBR",
            "BoundingBox": {
                "Width": 0.5711609125137329,
                "Height": 0.011506942100822926,
                "Left": 0.22337408363819122,
                "Top": 0.517551600933075
            },
            "Id": "31a52747-6203-4a37-ace3-a96325fc39af",
            "Quadrant": "Q3",
            "height_diff_above": 0.0021430784836411476,
            "height_diff_below": 0.0022417036816477776,
            "paragraph": 0,
            "paragraph_std": 1,
            "top_scl": 0.1303078298173228,
            "paragraph_scl": 0.0,
            "left_scl": 0.5118835812389761,
            "paragraph_std_scl": 0.5,
            "text_cluster": 2,
            "cluster_probability": 0.07800345515718904
        },
        {
            "BlockType": "LINE",
            "Confidnece": 99.88151550292969,
            "Text": "WEMI model. The original artwork (2D), the stele (3D), and the rubbing (2D) are treated",
            "BoundingBox": {
                "Width": 0.5905338525772095,
                "Height": 0.011521819047629833,
                "Left": 0.20411919057369232,
                "Top": 0.5313002467155457
            },
            "Id": "f9a7eaff-8b2a-434b-820a-ea78a45b683d",
            "Quadrant": "Q3",
            "height_diff_above": 0.0022417036816477776,
            "height_diff_below": 0.002313372679054737,
            "paragraph": 0,
            "paragraph_std": 1,
            "top_scl": 0.1740343174750314,
            "paragraph_scl": 0.0,
            "left_scl": 0.01832306748569401,
            "paragraph_std_scl": 0.5,
            "text_cluster": 2,
            "cluster_probability": 0.5497635370900372
        },
        {
            "BlockType": "LINE",
            "Confidnece": 99.06454467773438,
            "Text": "as three related Works. The creators (artist/calligrapher, engraver, technician) and",
            "BoundingBox": {
                "Width": 0.5902798175811768,
                "Height": 0.011529305949807167,
                "Left": 0.20458026230335236,
                "Top": 0.5451354384422302
            },
            "Id": "062bdbf8-8408-4e58-9dc9-b1988fcf6b1f",
            "Quadrant": "Q3",
            "height_diff_above": 0.002313372679054737,
            "height_diff_below": 0.001975676044821739,
            "paragraph": 0,
            "paragraph_std": 1,
            "top_scl": 0.21803605770825696,
            "paragraph_scl": 0.0,
            "left_scl": 0.030141715296712057,
            "paragraph_std_scl": 0.5,
            "text_cluster": 2,
            "cluster_probability": 1.0
        },
        {
            "BlockType": "LINE",
            "Confidnece": 99.89055633544922,
            "Text": "creation dates of the Works are different. Therefore, when cataloging a rubbing, Q would",
            "BoundingBox": {
                "Width": 0.590438187122345,
                "Height": 0.011644884943962097,
                "Left": 0.20420822501182556,
                "Top": 0.5586404204368591
            },
            "Id": "d3ee85bc-8a85-418f-8ba8-be98de263dae",
            "Quadrant": "Q3",
            "height_diff_above": 0.001975676044821739,
            "height_diff_below": 0.001962319016456604,
            "paragraph": 0,
            "paragraph_std": 1,
            "top_scl": 0.2609875918337945,
            "paragraph_scl": 0.0,
            "left_scl": 0.020605286497743514,
            "paragraph_std_scl": 0.5,
            "text_cluster": 2,
            "cluster_probability": 1.0
        },
        {
            "BlockType": "LINE",
            "Confidnece": 99.88599395751953,
            "Text": "record the creation date of the rubbing and the name of the technician, if applicable, as",
            "BoundingBox": {
                "Width": 0.5902219414710999,
                "Height": 0.01155180111527443,
                "Left": 0.20415964722633362,
                "Top": 0.5722476243972778
            },
            "Id": "24e01396-a1d1-4c9d-a7cd-54262b024664",
            "Quadrant": "Q3",
            "height_diff_above": 0.001962319016456604,
            "height_diff_below": 0.002310272306203842,
            "paragraph": 0,
            "paragraph_std": 1,
            "top_scl": 0.3042642348897804,
            "paragraph_scl": 0.0,
            "left_scl": 0.01936009252631532,
            "paragraph_std_scl": 0.5,
            "text_cluster": 2,
            "cluster_probability": 1.0
        },
        {
            "BlockType": "LINE",
            "Confidnece": 99.83655548095703,
            "Text": "the creator. However, Z does not agree with this approach. In an observation session with",
            "BoundingBox": {
                "Width": 0.590774416923523,
                "Height": 0.01149696484208107,
                "Left": 0.2040468454360962,
                "Top": 0.5861096978187561
            },
            "Id": "d351032f-798b-4cc7-ba65-7ee09b01a0bc",
            "Quadrant": "Q3",
            "height_diff_above": 0.002310272306203842,
            "height_diff_below": 0.0021847449243068695,
            "paragraph": 0,
            "paragraph_std": 1,
            "top_scl": 0.34835147024115876,
            "paragraph_scl": 0.0,
            "left_scl": 0.016468645175485186,
            "paragraph_std_scl": 0.5,
            "text_cluster": 2,
            "cluster_probability": 1.0
        },
        {
            "BlockType": "LINE",
            "Confidnece": 99.67897033691406,
            "Text": "Z, he elaborated on his rationale of cataloging rubbings as one work, and provided some",
            "BoundingBox": {
                "Width": 0.5910453200340271,
                "Height": 0.0114696454256773,
                "Left": 0.20366434752941132,
                "Top": 0.599791407585144
            },
            "Id": "83a2461d-686c-4dee-9e8d-cc428bc029fe",
            "Quadrant": "Q3",
            "height_diff_above": 0.0021847449243068695,
            "height_diff_below": 0.00205870158970356,
            "paragraph": 0,
            "paragraph_std": 1,
            "top_scl": 0.39186507315898766,
            "paragraph_scl": 0.0,
            "left_scl": 0.00666407951518444,
            "paragraph_std_scl": 0.5,
            "text_cluster": 2,
            "cluster_probability": 1.0
        },
        {
            "BlockType": "LINE",
            "Confidnece": 99.41151428222656,
            "Text": "cultural context. From Z's perspective, users only access the rubbing because they cannot",
            "BoundingBox": {
                "Width": 0.5907053351402283,
                "Height": 0.011757628060877323,
                "Left": 0.2041631042957306,
                "Top": 0.6133197546005249
            },
            "Id": "deca30c0-22cc-4e5f-8d5c-9748e5516542",
            "Quadrant": "Q3",
            "height_diff_above": 0.00205870158970356,
            "height_diff_below": 0.002025826834142208,
            "paragraph": 0,
            "paragraph_std": 1,
            "top_scl": 0.43489091789719914,
            "paragraph_scl": 0.0,
            "left_scl": 0.01944870755741146,
            "paragraph_std_scl": 0.5,
            "text_cluster": 2,
            "cluster_probability": 1.0
        },
        {
            "BlockType": "LINE",
            "Confidnece": 99.94239807128906,
            "Text": "access the original artwork or the stele. The original work may no longer exist, and the",
            "BoundingBox": {
                "Width": 0.5905224084854126,
                "Height": 0.011533999815583229,
                "Left": 0.20433694124221802,
                "Top": 0.6271032094955444
            },
            "Id": "3964f40f-d282-441a-9fa1-15f6ad88da14",
            "Quadrant": "Q3",
            "height_diff_above": 0.002025826834142208,
            "height_diff_below": 0.0019120331853628159,
            "paragraph": 0,
            "paragraph_std": 1,
            "top_scl": 0.47872811320236086,
            "paragraph_scl": 0.0,
            "left_scl": 0.02390466856068585,
            "paragraph_std_scl": 0.5,
            "text_cluster": 2,
            "cluster_probability": 1.0
        },
        {
            "BlockType": "LINE",
            "Confidnece": 99.90541076660156,
            "Text": "stele may be preserved at a museum. The rubbing is a reproduction of the original",
            "BoundingBox": {
                "Width": 0.58954256772995,
                "Height": 0.011617396958172321,
                "Left": 0.2043108195066452,
                "Top": 0.6405492424964905
            },
            "Id": "e0e7fc24-8f18-4c6d-a789-2428009c1164",
            "Quadrant": "Q3",
            "height_diff_above": 0.0019120331853628159,
            "height_diff_below": 0.00201501976698637,
            "paragraph": 0,
            "paragraph_std": 1,
            "top_scl": 0.5214921646852082,
            "paragraph_scl": 0.0,
            "left_scl": 0.023235090330038233,
            "paragraph_std_scl": 0.5,
            "text_cluster": 2,
            "cluster_probability": 1.0
        },
        {
            "BlockType": "LINE",
            "Confidnece": 99.75780487060547,
            "Text": "artwork. When cataloging rubbings, Z would record the artist/calligrapher and creation",
            "BoundingBox": {
                "Width": 0.5902195572853088,
                "Height": 0.011475914157927036,
                "Left": 0.20427975058555603,
                "Top": 0.6541816592216492
            },
            "Id": "a40633ca-8509-4d80-ba0d-4b681020fc34",
            "Quadrant": "Q3",
            "height_diff_above": 0.00201501976698637,
            "height_diff_below": 0.0020754998549818993,
            "paragraph": 0,
            "paragraph_std": 1,
            "top_scl": 0.5648489949584421,
            "paragraph_scl": 0.0,
            "left_scl": 0.022438700934201528,
            "paragraph_std_scl": 0.5,
            "text_cluster": 2,
            "cluster_probability": 1.0
        },
        {
            "BlockType": "LINE",
            "Confidnece": 99.64900970458984,
            "Text": "date of the original artwork, because that is what users care about. Z told me that in pre-",
            "BoundingBox": {
                "Width": 0.5909132957458496,
                "Height": 0.011475112289190292,
                "Left": 0.20406873524188995,
                "Top": 0.6677330732345581
            },
            "Id": "902b55c3-a7f4-4a89-b33b-7608c7d9baae",
            "Quadrant": "Q3",
            "height_diff_above": 0.0020754998549818993,
            "height_diff_below": 0.0023069120943546295,
            "paragraph": 0,
            "paragraph_std": 1,
            "top_scl": 0.6079482024698801,
            "paragraph_scl": 0.0,
            "left_scl": 0.017029746385309075,
            "paragraph_std_scl": 0.5,
            "text_cluster": 2,
            "cluster_probability": 1.0
        },
        {
            "BlockType": "LINE",
            "Confidnece": 99.66971588134766,
            "Text": "modern China, engravers and technicians are mechanics. They were not considered",
            "BoundingBox": {
                "Width": 0.5903611183166504,
                "Height": 0.011502869427204132,
                "Left": 0.20430707931518555,
                "Top": 0.681515097618103
            },
            "Id": "761a67c8-941b-4a14-b765-7da9d025c10d",
            "Quadrant": "Q3",
            "height_diff_above": 0.0023069120943546295,
            "height_diff_below": 0.0021842047572135925,
            "paragraph": 0,
            "paragraph_std": 1,
            "top_scl": 0.6517808481456944,
            "paragraph_scl": 0.0,
            "left_scl": 0.023139218033464637,
            "paragraph_std_scl": 0.5,
            "text_cluster": 2,
            "cluster_probability": 1.0
        },
        {
            "BlockType": "LINE",
            "Confidnece": 99.5284423828125,
            "Text": "creators of artworks. Hence, most of their names were not documented. Z commented:",
            "BoundingBox": {
                "Width": 0.580963671207428,
                "Height": 0.010602040216326714,
                "Left": 0.20404872298240662,
                "Top": 0.6952021718025208
            },
            "Id": "3ff322b5-7096-49bc-8ccf-2366d893306d",
            "Quadrant": "Q3",
            "height_diff_above": 0.0021842047572135925,
            "height_diff_below": 0.002714233472943306,
            "paragraph": 0,
            "paragraph_std": 1,
            "top_scl": 0.695311512173576,
            "paragraph_scl": 0.0,
            "left_scl": 0.01651677230444193,
            "paragraph_std_scl": 0.5,
            "text_cluster": 2,
            "cluster_probability": 0.5428785788759402
        },
        {
            "BlockType": "LINE",
            "Confidnece": 99.89382934570312,
            "Text": "\"How could it be helpful to users if we use RDA to catalog, and they see all",
            "BoundingBox": {
                "Width": 0.5334182977676392,
                "Height": 0.01194223016500473,
                "Left": 0.2424165904521942,
                "Top": 0.7085184454917908
            },
            "Id": "abf35635-8eea-47ad-8385-cedd8900e7a1",
            "Quadrant": "Q3",
            "height_diff_above": 0.002714233472943306,
            "height_diff_below": 0.001957215368747711,
            "paragraph": 0,
            "paragraph_std": 2,
            "top_scl": 0.7376628743610378,
            "paragraph_scl": 0.0,
            "left_scl": 1.0000000000000009,
            "paragraph_std_scl": 1.0,
            "text_cluster": 0,
            "cluster_probability": 0.1404010588346264
        },
        {
            "BlockType": "LINE",
            "Confidnece": 99.91572570800781,
            "Text": "these information [pointing at the author and publication information (creation date)",
            "BoundingBox": {
                "Width": 0.5576443672180176,
                "Height": 0.011742611415684223,
                "Left": 0.2231149673461914,
                "Top": 0.7224178910255432
            },
            "Id": "2775fdb5-c779-44d0-877d-0aa00651b99a",
            "Quadrant": "Q3",
            "height_diff_above": 0.001957215368747711,
            "height_diff_below": 0.0017863912507891655,
            "paragraph": 0,
            "paragraph_std": 2,
            "top_scl": 0.7818689687791165,
            "paragraph_scl": 0.0,
            "left_scl": 0.5052416554815657,
            "paragraph_std_scl": 1.0,
            "text_cluster": 0,
            "cluster_probability": 1.0
        },
        {
            "BlockType": "LINE",
            "Confidnece": 99.66773223876953,
            "Text": "fields] as \"unknown?\" This way of cataloging [RDA] cannot distinguish",
            "BoundingBox": {
                "Width": 0.5514171719551086,
                "Height": 0.012034212239086628,
                "Left": 0.2238697111606598,
                "Top": 0.7359468936920166
            },
            "Id": "b5e66f71-83bc-4206-b77f-e6e73efd2f5f",
            "Quadrant": "Q3",
            "height_diff_above": 0.0017863912507891655,
            "height_diff_below": 0.0017807139083743095,
            "paragraph": 0,
            "paragraph_std": 2,
            "top_scl": 0.8248968987641121,
            "paragraph_scl": 0.0,
            "left_scl": 0.5245879973996077,
            "paragraph_std_scl": 1.0,
            "text_cluster": 0,
            "cluster_probability": 1.0
        },
        {
            "BlockType": "LINE",
            "Confidnece": 99.46949768066406,
            "Text": "[rubbings] \"the original object is the critical element for identifying rubbings.\"",
            "BoundingBox": {
                "Width": 0.543770432472229,
                "Height": 0.011884006671607494,
                "Left": 0.2233329564332962,
                "Top": 0.7497618198394775
            },
            "Id": "172e7eb7-251e-4c0c-a90a-a642eef6b4a7",
            "Quadrant": "Q3",
            "height_diff_above": 0.0017807139083743095,
            "height_diff_below": 0.001824703998863697,
            "paragraph": 0,
            "paragraph_std": 2,
            "top_scl": 0.8688341859149162,
            "paragraph_scl": 0.0,
            "left_scl": 0.5108293679380127,
            "paragraph_std_scl": 1.0,
            "text_cluster": 0,
            "cluster_probability": 1.0
        },
        {
            "BlockType": "LINE",
            "Confidnece": 99.8779296875,
            "Text": "To explain the WEMI model, Q used an example of herself taking a picture of the",
            "BoundingBox": {
                "Width": 0.5717443823814392,
                "Height": 0.011842065490782261,
                "Left": 0.20340436697006226,
                "Top": 0.7634705305099487
            },
            "Id": "fca825e0-3190-4f24-a05d-2a7584993ca5",
            "Quadrant": "Q3",
            "height_diff_above": 0.001824703998863697,
            "height_diff_below": 0.002021915279328823,
            "paragraph": 0,
            "paragraph_std": 2,
            "top_scl": 0.912433663086677,
            "paragraph_scl": 0.0,
            "left_scl": 0.0,
            "paragraph_std_scl": 1.0,
            "text_cluster": 1,
            "cluster_probability": 1.0
        },
        {
            "BlockType": "LINE",
            "Confidnece": 99.82242584228516,
            "Text": "Mona Lisa painting at the Louvre. Da Vinci is the creator of the Mona Lisa painting,",
            "BoundingBox": {
                "Width": 0.5716721415519714,
                "Height": 0.011584064923226833,
                "Left": 0.20416146516799927,
                "Top": 0.7773345112800598
            },
            "Id": "7f594a6c-f0b1-4d2e-9411-2c3f981d7ab8",
            "Quadrant": "Q3",
            "height_diff_above": 0.002021915279328823,
            "height_diff_below": 0.0020848894491791725,
            "paragraph": 0,
            "paragraph_std": 2,
            "top_scl": 0.9565269646105186,
            "paragraph_scl": 0.0,
            "left_scl": 0.01940669180990895,
            "paragraph_std_scl": 1.0,
            "text_cluster": 1,
            "cluster_probability": 1.0
        },
        {
            "BlockType": "LINE",
            "Confidnece": 99.79964447021484,
            "Text": "and Q is the creator of the photo. Z argues that Da Vinci should be the creator of both",
            "BoundingBox": {
                "Width": 0.5717942714691162,
                "Height": 0.011652770452201366,
                "Left": 0.20419342815876007,
                "Top": 0.7910034656524658
            },
            "Id": "5ce2ed55-a574-45ba-8373-6402b7c85e49",
            "Quadrant": "Q3",
            "height_diff_above": 0.0020848894491791725,
            "height_diff_below": 0,
            "paragraph": 0,
            "paragraph_std": 2,
            "top_scl": 0.9999999999999998,
            "paragraph_scl": 0.0,
            "left_scl": 0.020225998886201246,
            "paragraph_std_scl": 1.0,
            "text_cluster": 1,
            "cluster_probability": 1.0
        }
    ],
    "file_name": "Sample 18.pdf"
}